{
  "file": "G2158838.mdx",
  "size": 7867249,
  "records": 137553,
  "ecu_name": "Door Ajar",
  "did_count": 74,
  "dids": {
    "205A": "Torque Steer Compensation Activation Counter",
    "205B": "Brake Pull Reduction Activation Counter",
    "3003": "Gear Hardware Part Number",
    "301A": "Pull Drift Compensation Value",
    "301F": "Steering Pinion Rotation Speed",
    "3020": "Steering Pinion Angle",
    "330C": "Steering Shaft Torque Sensor #2",
    "3B4B": "Steering wheel angle alignment offset",
    "630F": "Multiple VIN Storage-Original VIN",
    "D022": "In Progress OTA Download Address",
    "D026": "OTA Activation Preconditions",
    "D028": "Application Signature Validation Status",
    "D029": "OTA Over OVTP Support Level",
    "D02B": "OTA Software Update Counter",
    "D039": "OTA Partition Status",
    "D03B": "OTA Debug Information",
    "D03E": "In-Use OTA Command Signing Public Key Hash",
    "D03F": "In-Use Application Signing Public Key Hash",
    "D04F": "OTA ProgrammingSession Entry And A/B Swap Precondition Status",
    "D100": "Active Diagnostic Session",
    "D111": "ECU Power Supply Voltage",
    "D117": "ECU Internal Temperature",
    "D118": "Motor Current",
    "D700": "Critical Software Parameter Monitoring #1",
    "D701": "Critical Software Parameter Monitoring #2",
    "DD00": "Global Real Time",
    "DD01": "Total Distance",
    "DD05": "Outside temperature",
    "DD09": "Vehicle Speed",
    "DE00": "DID DE00 Vehicle Data",
    "DE01": "DID DE01 FIH SW Feature Config",
    "DE02": "DID DE02 Feature Config",
    "DE03": "DID DE03 Enable/Disable DTCs",
    "DE04": "DID DE04 PDC Reset Value",
    "DE05": "DID DE05 Unused",
    "EE00": "DID EE00 Dev Msg Config",
    "EE01": "DID EE01 XCP Enable/Disable",
    "EE02": "DID EE02 Assist On/Off",
    "EE03": "DID EE03 Ignition Cycle Counter",
    "EE04": "DID EE04 Ignition On Time",
    "EE05": "DID EE05 Final Motor Torque",
    "EE06": "DID EE06 VIN Changed",
    "EE07": "DID EE07 EPS System State",
    "EE20": "DID EE20 LoA Fault Reporting",
    "EE21": "DID EE21 Current Lvl Counters",
    "EE22": "DID EE22 Voltage Lvl Counters",
    "EE23": "DID EE23 Temperature Lvl Counters",
    "EE40": "DID EE40 Research Msg Config",
    "EE41": "DID EE41 Research Feature Switch",
    "EE42": "DID EE42 Active Features",
    "EE43": "DID EE43 SDM Steering Mode",
    "EE80": "DID EE80 FIH SW Version",
    "EE90": "Ford In House Failure Reason",
    "EED0": "DID EED0 Supplier Factory Mode",
    "EED1": "DID EED1 Supplier Internal Fault Code",
    "EED2": "SupplierInternalErrorMemory",
    "EED3": "SupplierInternalErrorMemory ECU2",
    "F10A": "ECU Cal-Config Part Number",
    "F110": "Subsystem Specific Diagnostic Specification Part Number",
    "F111": "ECU Core Assembly Number",
    "F113": "ECU Delivery Assembly Number",
    "F124": "ECU Calibration Data #1 Number",
    "F15F": "NOS Generation Tool Version Number",
    "F162": "Software Download Specification Version",
    "F163": "Diagnostic Specification Version",
    "F166": "NOS Message Database #1 Version Number",
    "F17C": "NOS Bootloader Generation Tool Version Number",
    "F17F": "Ford Electronic Serial Number",
    "F180": "Boot Software Identification",
    "F188": "Vehicle Manufacturer ECU Software Number",
    "F18A": "System Supplier Identifier",
    "F18C": "ECU Serial Number",
    "F190": "Vehicle Identification Number",
    "FD01": "Ford System State Fault Counter"
  },
  "routine_count": 7,
  "routines": {
    "0301": "Activate Secondary Boot-loader",
    "0304": "Check Valid Application",
    "200F": "Clear Steering Angle Centre Position Calibration",
    "DC00": "RTN DC00 Reset Assist Fault Counters",
    "F001": "RTN F001 Request Switch Signing Key",
    "FF00": "Flash Erase",
    "FF01": "Check Programming Dependencies"
  },
  "part_numbers": []
}