{
  "file": "G2158961.mdx",
  "size": 531229,
  "records": 7670,
  "ecu_name": "Door Ajar",
  "did_count": 101,
  "dids": {
    "0202": "Number of Trouble Codes Set due to Diagnostic Test",
    "2829": "Tire Pressure Monitoring System (TPMS) Radio Frequency Receiver (RFR) Sensor ID #1",
    "282A": "Tire Pressure Monitoring System (TPMS) Radio Frequency Receiver (RFR) Sensor ID #2",
    "282B": "Tire Pressure Monitoring System (TPMS) Radio Frequency Receiver (RFR) Sensor ID #3",
    "282C": "Tire Pressure Monitoring System (TPMS) Radio Frequency Receiver (RFR) Sensor ID #4",
    "282D": "Tire Pressure Monitoring System (TPMS) Radio Frequency Receiver (RFR) Sensor ID #5",
    "282E": "Tire Pressure Monitoring System (TPMS) Radio Frequency Receiver (RFR) Sensor ID #6",
    "424D": "Number of Peripheral Devices Programmed",
    "C211": "Last Received Transmitter ID Code (TIC) Value",
    "C243": "Programmed Transmitter ID Code (TIC) Value #1",
    "C244": "Programmed Transmitter ID Code (TIC) Value #2",
    "C245": "Programmed Transmitter ID Code (TIC) Value #3",
    "C246": "Programmed Transmitter ID Code (TIC) Value #4",
    "C247": "Programmed Transmitter ID Code (TIC) Value #5",
    "C252": "Programmed Transmitter ID Code (TIC) Value #6",
    "C253": "Programmed Transmitter ID Code (TIC) Value #7",
    "C254": "Programmed Transmitter ID Code (TIC) Value #8",
    "C255": "Programmed Transmitter ID Code (TIC) Value #9",
    "C256": "Programmed Transmitter ID Code (TIC) Value #10",
    "C25B": "Number of Programmed Remote Keyless Entry Transmittters",
    "D028": "Application Signature Validation Status",
    "D03F": "In-Use Application Signing Public Key Hash",
    "D04F": "OTA ProgrammingSession Entry And A/B Swap Precondition Status",
    "D100": "Active Diagnostic Session",
    "D111": "ECU Power Supply Voltage",
    "D700": "Critical Software Parameter Monitoring #1",
    "D701": "Critical Software Parameter Monitoring #2",
    "DE00": "Factory Configuration",
    "DE02": "MSCAN Data Test Modes",
    "DE03": "TPM Hibernate Config - 1",
    "DE04": "TPM Hibernate Config - 2",
    "DE05": "RKE Critical Polling Config",
    "DE06": "MSCAN Dev Test Data Config",
    "F110": "Subsystem Specific Diagnostic Specification Part Number",
    "F111": "ECU Core Assembly Number",
    "F113": "ECU Delivery Assembly Number",
    "F15B": "NOS Network Management Junior Version Number",
    "F15F": "NOS Generation Tool Version Number",
    "F162": "Software Download Specification Version",
    "F163": "Diagnostic Specification Version",
    "F166": "NOS Message Database #1 Version Number",
    "F17C": "NOS Bootloader Generation Tool Version Number",
    "F180": "Boot Software Identification",
    "F188": "Vehicle Manufacturer ECU Software Number",
    "F18C": "ECU Serial Number",
    "F1F3": "ECU - PBL SW Part Number - Supplier",
    "F1F4": "ECU - Base Model Part number - Supplier",
    "F1F5": "MCU Logic SW Part number - Supplier",
    "F1F7": "ECU - UHF IC Version Number",
    "F1F8": "ECU - PBL build ID",
    "F1F9": "MCU Logic SW Build ID",
    "F1FA": "ECU UHF IC User Flash SW Build ID",
    "F1FB": "MCU SW Fingerprint",
    "F1FC": "ECU HW Fingerprint",
    "F1FD": "ECU - HW_Variant_ID",
    "F1FE": "ECU - HW_SW Version ID",
    "FD00": "Remote Keyless Entry (RKE) Last RX RF Data Message",
    "FD01": "Last RX PEPS RF Data",
    "FD02": "Remote Keyless Entry (RKE) Last Received Action Code",
    "FD03": "RTM Voltage Monitoring Status",
    "FD04": "RTM Power Moding Operation",
    "FD08": "Last TPM Tranmitter ID",
    "FD0D": "Last RKE Acknowledgement Transmission Data",
    "FD10": "RSSI Avg for Last RX RKE Data Message",
    "FD11": "RSSI Avg for Last RX TPM Data Message",
    "FD17": "Runtime measurement: Max. CPU load",
    "FD18": "Runtime measurement: Max. interrupt lock time",
    "FD2A": "RTM RX Operation Status",
    "FD2C": "Tire Pressure Management (TPM) Last RX RF Data Message",
    "FD2D": "RTM TX Operation Status",
    "FD2E": "RTM KLine Operation Status",
    "FD2F": "RTM KLine BUS Reset Counter",
    "FD30": "Number of error history entries",
    "FD31": "Error History Entry 1",
    "FD32": "Error History Entry 2",
    "FD33": "Error History Entry 3",
    "FD34": "Error History Entry 4",
    "FD35": "Error History Entry 5",
    "FD36": "Error History Entry 6",
    "FD37": "Error History Entry 7",
    "FD38": "Error History Entry 8",
    "FD39": "Error History Entry 9",
    "FD3A": "KLine TX Data - Last Message",
    "FD3B": "KLine TX Data - 2nd to Last Message",
    "FD3C": "KLine RX Data - Last Message",
    "FD3D": "KLine RX Data - 2nd to Last Message",
    "FD3F": "KLine Op Parameters",
    "FD40": "Error History Entry 10",
    "FD43": "KOL / Body Info Status",
    "FD48": "KLine Mirror mode AUTOOFF counter",
    "FD4B": "RKE Action Type Clear timer value",
    "FD4D": "TPMS Frame Counters",
    "FD4F": "Raw A/D Data",
    "FD50": "RKE1-Ant2 Tx Attenuation Cal data",
    "FD51": "RKE1-Ant3 Tx Attenuation Cal data",
    "FD52": "RKE2-Ant2 Tx Attenuation Cal data",
    "FD53": "RKE2-Ant3 Tx Attenuation Cal data",
    "FD60": "UHF IC TIC Data",
    "FD61": "SCB Backup variable data",
    "FD62": "RFDrv Events Statistic Counters Read",
    "FD63": "RFDrv Frames Statistic Counters Read"
  },
  "routine_count": 19,
  "routines": {
    "0202": "On-Demand Self-Test",
    "020B": "Restore Initial ECU Configuration To Not Complete State",
    "0301": "Activate Secondary Boot-loader",
    "0304": "Check Valid Application",
    "FD2B": "Clear RKE TIC - TPM ID Data",
    "FD3E": "KLine Buffer Purge",
    "FD42": "Clear all error history data",
    "FD49": "Manufacturing calculation of Software Strategy Checksum",
    "FD4C": "Clear TPM Frame Counters",
    "FD54": "MFG I/O - Sleep IOD Check",
    "FD55": "MFG I/O: UHF IC programming Status",
    "FD56": "MFG I/O: UHF Tx Test",
    "FD57": "MFG I/O: UHF Rx Test",
    "FD58": "UHF IC Internal TIC Check",
    "FD5A": "RFDrv Statistic Counters Clear",
    "FD5B": "MCU Op Status - Interrupt Run Time measurement.",
    "FD5C": "MCU Op Status - Task Runtime Measurement",
    "FF00": "Flash Erase",
    "FF01": "Check Programming Dependencies"
  },
  "part_numbers": []
}